formatter/__init__.py
formatter/formatter.py
42formatter-0.1.2.dist-info/METADATA
42formatter-0.1.2.dist-info/WHEEL
42formatter-0.1.2.dist-info/entry_points.txt
42formatter-0.1.2.dist-info/top_level.txt
42formatter-0.1.2.dist-info/RECORD
