Metadata-Version: 2.1
Name: 42formatter
Version: 0.1.2
Summary: format input file(s) to 42 norm automatically
Home-page: https://github.com/Twatwane/42formatter
Author: Antoine Josse
Author-email: ajosse@student.42.fr
Classifier: Programming Language :: Python :: 3
Classifier: License :: Other/Proprietary License
Classifier: Operating System :: OS Independent
Requires-Python: >=3.6
